html_tree_shaking/__init__.py
html_tree_shaking/shaking.py
html_tree_shaking/.bin/html-tree-shaking-linux
html_tree_shaking-1.0.9.dist-info/METADATA
html_tree_shaking-1.0.9.dist-info/WHEEL
html_tree_shaking-1.0.9.dist-info/top_level.txt
html_tree_shaking-1.0.9.dist-info/RECORD
