Metadata-Version: 2.1
Name: html_tree_shaking
Version: 1.0.9
Summary: HTML tree shaking
Home-page: https://www.clicknium.com/documents
Author-email: clicknium@clicknium.com
